freecad_mcp/__init__.py
freecad_mcp/py.typed
freecad_mcp/server.py
freecad_mcp-0.1.15.dist-info/METADATA
freecad_mcp-0.1.15.dist-info/WHEEL
freecad_mcp-0.1.15.dist-info/entry_points.txt
freecad_mcp-0.1.15.dist-info/licenses/LICENSE
freecad_mcp-0.1.15.dist-info/RECORD
