Metadata-Version: 2.4
Name: freecad-mcp
Version: 0.1.15
Summary: Add your description here
Author-email: neka-nat <nekanat.stock@gmail.com>
License: MIT
License-File: LICENSE
Requires-Python: >=3.12
Requires-Dist: mcp[cli]>=1.12.2
